pinax/__init__.py
pinax/forums/__init__.py
pinax/forums/admin.py
pinax/forums/apps.py
pinax/forums/compat.py
pinax/forums/conf.py
pinax/forums/forms.py
pinax/forums/hooks.py
pinax/forums/managers.py
pinax/forums/models.py
pinax/forums/receivers.py
pinax/forums/urls.py
pinax/forums/views.py
pinax/forums/migrations/0001_initial.py
pinax/forums/migrations/__init__.py
pinax/forums/templatetags/__init__.py
pinax/forums/templatetags/pinax_forums_tags.py
pinax/forums/tests/__init__.py
pinax/forums/tests/tests.py
pinax/forums/tests/urls.py
pinax_forums-2.0.0.dist-info/AUTHORS
pinax_forums-2.0.0.dist-info/LICENSE
pinax_forums-2.0.0.dist-info/METADATA
pinax_forums-2.0.0.dist-info/WHEEL
pinax_forums-2.0.0.dist-info/top_level.txt
pinax_forums-2.0.0.dist-info/RECORD
